MANIFEST.in
README.rst
setup.cfg
setup.py
examples/__init__.py
examples/get_games_for_team.py
examples/get_players_for_season.py
nba_data/__init__.py
nba_data/client.py
nba_data.egg-info/PKG-INFO
nba_data.egg-info/SOURCES.txt
nba_data.egg-info/dependency_links.txt
nba_data.egg-info/requires.txt
nba_data.egg-info/top_level.txt
nba_data/data/__init__.py
nba_data/data/base_query_parameter.py
nba_data/data/box_scores.py
nba_data/data/current_season_only.py
nba_data/data/date_range.py
nba_data/data/game.py
nba_data/data/injury_details.py
nba_data/data/league.py
nba_data/data/matchup.py
nba_data/data/outcome.py
nba_data/data/player_news_item.py
nba_data/data/player_status.py
nba_data/data/players.py
nba_data/data/position.py
nba_data/data/season.py
nba_data/data/season_range.py
nba_data/data/season_type.py
nba_data/data/team.py
nba_data/data/team_season_range.py
nba_data/data/unit.py
nba_data/deserializers/__init__.py
nba_data/deserializers/calendar.py
nba_data/deserializers/common_all_players.py
nba_data/deserializers/common_player_info.py
nba_data/deserializers/scoreboard.py
nba_data/deserializers/season_players.py
nba_data/deserializers/team_game_log.py
nba_data/deserializers/box_scores/__init__.py
nba_data/deserializers/box_scores/advanced.py
nba_data/deserializers/box_scores/game.py
nba_data/deserializers/box_scores/traditional.py
nba_data/deserializers/roto_wire/__init__.py
nba_data/deserializers/roto_wire/player_news_item.py
nba_data/deserializers/roto_wire/player_news_items.py
nba_data/deserializers/roto_wire/test_rotoWirePlayerNewsItemsDeserializer.py
nba_data/deserializers/utils/__init__.py
nba_data/deserializers/utils/advanced_box_score_deserializer_utils.py
nba_data/deserializers/utils/box_score_deserializer_utils.py
nba_data/nba_stats_api_utils/__init__.py
nba_data/nba_stats_api_utils/query_parameter_generator.py
nba_data/nba_stats_api_utils/uri_generator.py