Metadata-Version: 1.1
Name: nba-data
Version: 1.9.2
Summary: An NBA Stats Client
Home-page: https://github.com/jaebradley/nba_data
Author: Jae Bradley
Author-email: jae.b.bradley@gmail.com
License: UNKNOWN
Download-URL: https://github.com/jaebradley/nba_data/tarball/1.9.2
Keywords: nba,nba_data
Platform: UNKNOWN
Classifier: Development Status :: 3 - Alpha
Classifier: Programming Language :: Python :: 2.7
